Workbook

Sheet Portfolio Dashboard
A1: Portfolio Finance Dashboard
A2: Engagement Finance Toolkit -- synthetic data, as of 2025-08-15
A3: Total Portfolio Budget | D3: Total Actual $ to Date | G3: Portfolio Utilization % | J3: Engagements Over Budget | M3: Open Exceptions | P3: High-Severity Exceptions
A4: =SUM('Engagement Summary'!I4:I21) -> 6603130 | D4: =SUM('Engagement Summary'!O4:O21) -> 5127914 | G4: =SUM('Engagement Summary'!N4:N21)/SUM('Engagement Summary'!H4:H21) -> 0.77647475 | J4: =COUNTIF('Engagement Summary'!S4:S21,"Over Budget") -> 0 | M4: =COUNTA('Discrepancy Report'!A4:A67) -> 64 | P4: =COUNTIF('Discrepancy Report'!F4:F67,"High") -> 19
A7: Monthly Portfolio Trend
A8: Month | B8: Budgeted Hours | C8: Actual Hours | D8: Utilization % | E8: Actual $ (Standard) | F8: Actual $ (Recorded) | G8: Realization %
A9: 45566 | B9: =SUMIFS('Budget vs Actual'!$E$4:$E$515,'Budget vs Actual'!$D$4:$D$515,A9) -> 211.26 | C9: =SUMIFS('Budget vs Actual'!$F$4:$F$515,'Budget vs Actual'!$D$4:$D$515,A9) -> 161.1 | D9: =IF(B9=0,"",C9/B9) -> 0.76256745 | E9: =SUMIFS('Budget vs Actual'!$I$4:$I$515,'Budget vs Actual'!$D$4:$D$515,A9) -> 33665.5 | F9: =SUMIFS('Budget vs Actual'!$J$4:$J$515,'Budget vs Actual'!$D$4:$D$515,A9) -> 33665.5 | G9: =IF(E9=0,"",F9/E9) -> 1
A10: 45597 | B10: =SUMIFS('Budget vs Actual'!$E$4:$E$515,'Budget vs Actual'!$D$4:$D$515,A10) -> 695.71 | C10: =SUMIFS('Budget vs Actual'!$F$4:$F$515,'Budget vs Actual'!$D$4:$D$515,A10) -> 599.1 | D10: =IF(B10=0,"",C10/B10) -> 0.86113467 | E10: =SUMIFS('Budget vs Actual'!$I$4:$I$515,'Budget vs Actual'!$D$4:$D$515,A10) -> 127456 | F10: =SUMIFS('Budget vs Actual'!$J$4:$J$515,'Budget vs Actual'!$D$4:$D$515,A10) -> 127599 | G10: =IF(E10=0,"",F10/E10) -> 1.001122
A11: 45627 | B11: =SUMIFS('Budget vs Actual'!$E$4:$E$515,'Budget vs Actual'!$D$4:$D$515,A11) -> 1210.85 | C11: =SUMIFS('Budget vs Actual'!$F$4:$F$515,'Budget vs Actual'!$D$4:$D$515,A11) -> 1117.1 | D11: =IF(B11=0,"",C11/B11) -> 0.92257505 | E11: =SUMIFS('Budget vs Actual'!$I$4:$I$515,'Budget vs Actual'!$D$4:$D$515,A11) -> 237530 | F11: =SUMIFS('Budget vs Actual'!$J$4:$J$515,'Budget vs Actual'!$D$4:$D$515,A11) -> 237967.5 | G11: =IF(E11=0,"",F11/E11) -> 1.0018419
A12: 45658 | B12: =SUMIFS('Budget vs Actual'!$E$4:$E$515,'Budget vs Actual'!$D$4:$D$515,A12) -> 1592.92 | C12: =SUMIFS('Budget vs Actual'!$F$4:$F$515,'Budget vs Actual'!$D$4:$D$515,A12) -> 1515.7 | D12: =IF(B12=0,"",C12/B12) -> 0.95152299 | E12: =SUMIFS('Budget vs Actual'!$I$4:$I$515,'Budget vs Actual'!$D$4:$D$515,A12) -> 321468.5 | F12: =SUMIFS('Budget vs Actual'!$J$4:$J$515,'Budget vs Actual'!$D$4:$D$515,A12) -> 320580.5 | G12: =IF(E12=0,"",F12/E12) -> 0.99723768
A13: 45689 | B13: =SUMIFS('Budget vs Actual'!$E$4:$E$515,'Budget vs Actual'!$D$4:$D$515,A13) -> 2160.24 | C13: =SUMIFS('Budget vs Actual'!$F$4:$F$515,'Budget vs Actual'!$D$4:$D$515,A13) -> 2135.3 | D13: =IF(B13=0,"",C13/B13) -> 0.98845499 | E13: =SUMIFS('Budget vs Actual'!$I$4:$I$515,'Budget vs Actual'!$D$4:$D$515,A13) -> 456569 | F13: =SUMIFS('Budget vs Actual'!$J$4:$J$515,'Budget vs Actual'!$D$4:$D$515,A13) -> 457508 | G13: =IF(E13=0,"",F13/E13) -> 1.0020566
A14: 45717 | B14: =SUMIFS('Budget vs Actual'!$E$4:$E$515,'Budget vs Actual'!$D$4:$D$515,A14) -> 2610.86 | C14: =SUMIFS('Budget vs Actual'!$F$4:$F$515,'Budget vs Actual'!$D$4:$D$515,A14) -> 2767.4 | D14: =IF(B14=0,"",C14/B14) -> 1.0599573 | E14: =SUMIFS('Budget vs Actual'!$I$4:$I$515,'Budget vs Actual'!$D$4:$D$515,A14) -> 582630.5 | F14: =SUMIFS('Budget vs Actual'!$J$4:$J$515,'Budget vs Actual'!$D$4:$D$515,A14) -> 585181.5 | G14: =IF(E14=0,"",F14/E14) -> 1.0043784
A15: 45748 | B15: =SUMIFS('Budget vs Actual'!$E$4:$E$515,'Budget vs Actual'!$D$4:$D$515,A15) -> 2803.77 | C15: =SUMIFS('Budget vs Actual'!$F$4:$F$515,'Budget vs Actual'!$D$4:$D$515,A15) -> 3150.7 | D15: =IF(B15=0,"",C15/B15) -> 1.123737 | E15: =SUMIFS('Budget vs Actual'!$I$4:$I$515,'Budget vs Actual'!$D$4:$D$515,A15) -> 670385 | F15: =SUMIFS('Budget vs Actual'!$J$4:$J$515,'Budget vs Actual'!$D$4:$D$515,A15) -> 670953 | G15: =IF(E15=0,"",F15/E15) -> 1.0008473
A16: 45778 | B16: =SUMIFS('Budget vs Actual'!$E$4:$E$515,'Budget vs Actual'!$D$4:$D$515,A16) -> 2886.81 | C16: =SUMIFS('Budget vs Actual'!$F$4:$F$515,'Budget vs Actual'!$D$4:$D$515,A16) -> 3492.1 | D16: =IF(B16=0,"",C16/B16) -> 1.2096743 | E16: =SUMIFS('Budget vs Actual'!$I$4:$I$515,'Budget vs Actual'!$D$4:$D$515,A16) -> 742682.5 | F16: =SUMIFS('Budget vs Actual'!$J$4:$J$515,'Budget vs Actual'!$D$4:$D$515,A16) -> 743284.5 | G16: =IF(E16=0,"",F16/E16) -> 1.0008106
A17: 45809 | B17: =SUMIFS('Budget vs Actual'!$E$4:$E$515,'Budget vs Actual'!$D$4:$D$515,A17) -> 2766.21 | C17: =SUMIFS('Budget vs Actual'!$F$4:$F$515,'Budget vs Actual'!$D$4:$D$515,A17) -> 3966.3 | D17: =IF(B17=0,"",C17/B17) -> 1.4338391 | E17: =SUMIFS('Budget vs Actual'!$I$4:$I$515,'Budget vs Actual'!$D$4:$D$515,A17) -> 843966 | F17: =SUMIFS('Budget vs Actual'!$J$4:$J$515,'Budget vs Actual'!$D$4:$D$515,A17) -> 848766.5 | G17: =IF(E17=0,"",F17/E17) -> 1.005688
A18: 45839 | B18: =SUMIFS('Budget vs Actual'!$E$4:$E$515,'Budget vs Actual'!$D$4:$D$515,A18) -> 2510.16 | C18: =SUMIFS('Budget vs Actual'!$F$4:$F$515,'Budget vs Actual'!$D$4:$D$515,A18) -> 3588.8 | D18: =IF(B18=0,"",C18/B18) -> 1.4297097 | E18: =SUMIFS('Budget vs Actual'!$I$4:$I$515,'Budget vs Actual'!$D$4:$D$515,A18) -> 758340 | F18: =SUMIFS('Budget vs Actual'!$J$4:$J$515,'Budget vs Actual'!$D$4:$D$515,A18) -> 759442.5 | G18: =IF(E18=0,"",F18/E18) -> 1.0014538
A19: 45870 | B19: =SUMIFS('Budget vs Actual'!$E$4:$E$515,'Budget vs Actual'!$D$4:$D$515,A19) -> 2212.15 | C19: =SUMIFS('Budget vs Actual'!$F$4:$F$515,'Budget vs Actual'!$D$4:$D$515,A19) -> 1660.2 | D19: =IF(B19=0,"",C19/B19) -> 0.7504916 | E19: =SUMIFS('Budget vs Actual'!$I$4:$I$515,'Budget vs Actual'!$D$4:$D$515,A19) -> 353221 | F19: =SUMIFS('Budget vs Actual'!$J$4:$J$515,'Budget vs Actual'!$D$4:$D$515,A19) -> 353221 | G19: =IF(E19=0,"",F19/E19) -> 1
A21: Open Exceptions by Severity
A22: Severity | B22: Count | C22: $ Impact
A23: High | B23: =COUNTIF('Discrepancy Report'!F4:F67,A23) -> 19 | C23: =SUMIF('Discrepancy Report'!F4:F67,A23,'Discrepancy Report'!G4:G67) -> 152639
A24: Medium | B24: =COUNTIF('Discrepancy Report'!F4:F67,A24) -> 28 | C24: =SUMIF('Discrepancy Report'!F4:F67,A24,'Discrepancy Report'!G4:G67) -> 70151.5
A25: Low | B25: =COUNTIF('Discrepancy Report'!F4:F67,A25) -> 17 | C25: =SUMIF('Discrepancy Report'!F4:F67,A25,'Discrepancy Report'!G4:G67) -> 116848.32

Sheet Engagement Summary
A1: Engagement Portfolio Summary
A2: Synthetic data, as of 2025-08-15 -- for portfolio demonstration only
A3: Engagement ID | B3: Client | C3: Engagement Name | D3: Contract Type | E3: Engagement Leader | F3: Start Date | G3: End Date | H3: Budgeted Hours | I3: Budgeted $ | J3: Contract Ceiling $ | K3: Change Order $ | L3: Approved Ceiling $ | M3: Schedule % Elapsed | N3: Actual Hours to Date | O3: Actual $ to Date | P3: Utilization % | Q3: % of Ceiling Consumed | R3: Budget/Schedule Variance | S3: Status | T3: Open Exceptions | U3: Total Exception $ Impact | V3: Ceiling Basis $ to Date
A4: ENG-001 | B4: Commonwealth Department of Transportation | C4: Highway Asset Management Program Support | D4: Fixed-Fee | E4: M. Alvarez | F4: 45588 | G4: 45795 | H4: 2104 | I4: 449785 | J4: 449785 | K4: 52794.37 | L4: =J4+K4 -> 502579.37 | M4: 1 | N4: =SUMIFS('Budget vs Actual'!$F$4:$F$515,'Budget vs Actual'!$A$4:$A$515,A4) -> 1772 | O4: =SUMIFS('Budget vs Actual'!$I$4:$I$515,'Budget vs Actual'!$A$4:$A$515,A4) -> 381620 | P4: =IF(H4=0,"",N4/H4) -> 0.84220532 | Q4: =IF(L4=0,"",V4/L4) -> 0.75932285 | R4: =P4-M4 -> -0.15779468 | S4: =IF(P4>1,"Over Budget",IF(R4>0.15,"Trending Over Budget",IF(R4<-0.15,"Behind Pace / Under-Utilized","On Track"))) -> Behind Pace / Under-Utilized | T4: =COUNTIF('Discrepancy Report'!$B$4:$B$67,A4) -> 4 | U4: =SUMIF('Discrepancy Report'!$B$4:$B$67,A4,'Discrepancy Report'!$G$4:$G$67) -> 10694.5 | V4: 381620
A5: ENG-002 | B5: Bureau of Health & Human Services | C5: Medicaid Eligibility System Modernization PMO | D5: Fixed-Fee | E5: R. Chen | F5: 45602 | G5: 45847 | H5: 1159 | I5: 246725 | J5: 246725 | K5: 0 | L5: =J5+K5 -> 246725 | M5: 1 | N5: =SUMIFS('Budget vs Actual'!$F$4:$F$515,'Budget vs Actual'!$A$4:$A$515,A5) -> 953.8 | O5: =SUMIFS('Budget vs Actual'!$I$4:$I$515,'Budget vs Actual'!$A$4:$A$515,A5) -> 203218.5 | P5: =IF(H5=0,"",N5/H5) -> 0.82295082 | Q5: =IF(L5=0,"",V5/L5) -> 0.823664 | R5: =P5-M5 -> -0.17704918 | S5: =IF(P5>1,"Over Budget",IF(R5>0.15,"Trending Over Budget",IF(R5<-0.15,"Behind Pace / Under-Utilized","On Track"))) -> Behind Pace / Under-Utilized | T5: =COUNTIF('Discrepancy Report'!$B$4:$B$67,A5) -> 4 | U5: =SUMIF('Discrepancy Report'!$B$4:$B$67,A5,'Discrepancy Report'!$G$4:$G$67) -> 10036.5 | V5: 203218.5
A6: ENG-003 | B6: Federal Logistics & Readiness Agency | C6: Logistics Readiness ERP Modernization PMO | D6: Cost-Plus-Fixed-Fee | E6: M. Alvarez | F6: 45701 | G6: 45952 | H6: 1277 | I6: 272510 | J6: 162229.64 | K6: 0 | L6: =J6+K6 -> 162229.64 | M6: 0.848 | N6: =SUMIFS('Budget vs Actual'!$F$4:$F$515,'Budget vs Actual'!$A$4:$A$515,A6) -> 1068.6 | O6: =SUMIFS('Budget vs Actual'!$I$4:$I$515,'Budget vs Actual'!$A$4:$A$515,A6) -> 225681.5 | P6: =IF(H6=0,"",N6/H6) -> 0.83680501 | Q6: =IF(L6=0,"",V6/L6) -> 0.81892335 | R6: =P6-M6 -> -0.011194988 | S6: =IF(P6>1,"Over Budget",IF(R6>0.15,"Trending Over Budget",IF(R6<-0.15,"Behind Pace / Under-Utilized","On Track"))) -> On Track | T6: =COUNTIF('Discrepancy Report'!$B$4:$B$67,A6) -> 2 | U6: =SUMIF('Discrepancy Report'!$B$4:$B$67,A6,'Discrepancy Report'!$G$4:$G$67) -> 8394.5 | V6: 132853.64
A7: ENG-004 | B7: Ashford County Government | C7: County Financial Systems Upgrade Support | D7: Cost-Plus-Fixed-Fee | E7: M. Alvarez | F7: 45598 | G7: 45975 | H7: 2894 | I7: 614015 | J7: 397488.71 | K7: 59655.92 | L7: =J7+K7 -> 457144.63 | M7: 0.833 | N7: =SUMIFS('Budget vs Actual'!$F$4:$F$515,'Budget vs Actual'!$A$4:$A$515,A7) -> 1744 | O7: =SUMIFS('Budget vs Actual'!$I$4:$I$515,'Budget vs Actual'!$A$4:$A$515,A7) -> 372266 | P7: =IF(H7=0,"",N7/H7) -> 0.60262612 | Q7: =IF(L7=0,"",V7/L7) -> 0.49278052 | R7: =P7-M7 -> -0.23037388 | S7: =IF(P7>1,"Over Budget",IF(R7>0.15,"Trending Over Budget",IF(R7<-0.15,"Behind Pace / Under-Utilized","On Track"))) -> Behind Pace / Under-Utilized | T7: =COUNTIF('Discrepancy Report'!$B$4:$B$67,A7) -> 4 | U7: =SUMIF('Discrepancy Report'!$B$4:$B$67,A7,'Discrepancy Report'!$G$4:$G$67) -> 9749.5 | V7: 225271.97
A8: ENG-005 | B8: Metro Regional Transit Authority | C8: Capital Projects Cost Control Advisory | D8: Fixed-Fee | E8: R. Chen | F8: 45718 | G8: 45971 | H8: 2810 | I8: 593475 | J8: 593475 | K8: 0 | L8: =J8+K8 -> 593475 | M8: 0.722 | N8: =SUMIFS('Budget vs Actual'!$F$4:$F$515,'Budget vs Actual'!$A$4:$A$515,A8) -> 2385.5 | O8: =SUMIFS('Budget vs Actual'!$I$4:$I$515,'Budget vs Actual'!$A$4:$A$515,A8) -> 505278 | P8: =IF(H8=0,"",N8/H8) -> 0.84893238 | Q8: =IF(L8=0,"",V8/L8) -> 0.85138885 | R8: =P8-M8 -> 0.12693238 | S8: =IF(P8>1,"Over Budget",IF(R8>0.15,"Trending Over Budget",IF(R8<-0.15,"Behind Pace / Under-Utilized","On Track"))) -> On Track | T8: =COUNTIF('Discrepancy Report'!$B$4:$B$67,A8) -> 4 | U8: =SUMIF('Discrepancy Report'!$B$4:$B$67,A8,'Discrepancy Report'!$G$4:$G$67) -> 14848.5 | V8: 505278
A9: ENG-006 | B9: Commonwealth Department of Transportation | C9: Capital Program Financial Advisory | D9: Cost-Plus-Fixed-Fee | E9: R. Chen | F9: 45631 | G9: 46148 | H9: 4106 | I9: 870360 | J9: 510577.09 | K9: 0 | L9: =J9+K9 -> 510577.09 | M9: 0.5 | N9: =SUMIFS('Budget vs Actual'!$F$4:$F$515,'Budget vs Actual'!$A$4:$A$515,A9) -> 2462.7 | O9: =SUMIFS('Budget vs Actual'!$I$4:$I$515,'Budget vs Actual'!$A$4:$A$515,A9) -> 522527.5 | P9: =IF(H9=0,"",N9/H9) -> 0.59978081 | Q9: =IF(L9=0,"",V9/L9) -> 0.59917659 | R9: =P9-M9 -> 0.099780809 | S9: =IF(P9>1,"Over Budget",IF(R9>0.15,"Trending Over Budget",IF(R9<-0.15,"Behind Pace / Under-Utilized","On Track"))) -> On Track | T9: =COUNTIF('Discrepancy Report'!$B$4:$B$67,A9) -> 4 | U9: =SUMIF('Discrepancy Report'!$B$4:$B$67,A9,'Discrepancy Report'!$G$4:$G$67) -> 24633 | V9: 305925.84
A10: ENG-007 | B10: Bureau of Health & Human Services | C10: Provider Payment Integrity Review | D10: Fixed-Fee | E10: R. Chen | F10: 45678 | G10: 45769 | H10: 236 | I10: 50595 | J10: 50595 | K10: 4734.19 | L10: =J10+K10 -> 55329.19 | M10: 1 | N10: =SUMIFS('Budget vs Actual'!$F$4:$F$515,'Budget vs Actual'!$A$4:$A$515,A10) -> 205.3 | O10: =SUMIFS('Budget vs Actual'!$I$4:$I$515,'Budget vs Actual'!$A$4:$A$515,A10) -> 42484.5 | P10: =IF(H10=0,"",N10/H10) -> 0.86991525 | Q10: =IF(L10=0,"",V10/L10) -> 0.76784966 | R10: =P10-M10 -> -0.13008475 | S10: =IF(P10>1,"Over Budget",IF(R10>0.15,"Trending Over Budget",IF(R10<-0.15,"Behind Pace / Under-Utilized","On Track"))) -> On Track | T10: =COUNTIF('Discrepancy Report'!$B$4:$B$67,A10) -> 0 | U10: =SUMIF('Discrepancy Report'!$B$4:$B$67,A10,'Discrepancy Report'!$G$4:$G$67) -> 0 | V10: 42484.5
A11: ENG-008 | B11: Federal Logistics & Readiness Agency | C11: Supply Chain Cost Accounting Advisory | D11: Time & Materials | E11: R. Chen | F11: 45776 | G11: 46195 | H11: 1194 | I11: 256650 | J11: 263798.86 | K11: 55201.81 | L11: =J11+K11 -> 319000.67 | M11: 0.284 | N11: =SUMIFS('Budget vs Actual'!$F$4:$F$515,'Budget vs Actual'!$A$4:$A$515,A11) -> 1032 | O11: =SUMIFS('Budget vs Actual'!$I$4:$I$515,'Budget vs Actual'!$A$4:$A$515,A11) -> 222334 | P11: =IF(H11=0,"",N11/H11) -> 0.86432161 | Q11: =IF(L11=0,"",V11/L11) -> 0.69697032 | R11: =P11-M11 -> 0.58032161 | S11: =IF(P11>1,"Over Budget",IF(R11>0.15,"Trending Over Budget",IF(R11<-0.15,"Behind Pace / Under-Utilized","On Track"))) -> Trending Over Budget | T11: =COUNTIF('Discrepancy Report'!$B$4:$B$67,A11) -> 4 | U11: =SUMIF('Discrepancy Report'!$B$4:$B$67,A11,'Discrepancy Report'!$G$4:$G$67) -> 4153 | V11: 222334
A12: ENG-009 | B12: Ashford County Government | C12: Procurement Process Improvement Study | D12: Cost-Plus-Fixed-Fee | E12: D. Okoro | F12: 45616 | G12: 45821 | H12: 2492 | I12: 529510 | J12: 319379.48 | K12: 0 | L12: =J12+K12 -> 319379.48 | M12: 1 | N12: =SUMIFS('Budget vs Actual'!$F$4:$F$515,'Budget vs Actual'!$A$4:$A$515,A12) -> 2071.8 | O12: =SUMIFS('Budget vs Actual'!$I$4:$I$515,'Budget vs Actual'!$A$4:$A$515,A12) -> 440190.5 | P12: =IF(H12=0,"",N12/H12) -> 0.83138042 | Q12: =IF(L12=0,"",V12/L12) -> 0.80552414 | R12: =P12-M12 -> -0.16861958 | S12: =IF(P12>1,"Over Budget",IF(R12>0.15,"Trending Over Budget",IF(R12<-0.15,"Behind Pace / Under-Utilized","On Track"))) -> Behind Pace / Under-Utilized | T12: =COUNTIF('Discrepancy Report'!$B$4:$B$67,A12) -> 6 | U12: =SUMIF('Discrepancy Report'!$B$4:$B$67,A12,'Discrepancy Report'!$G$4:$G$67) -> 101264.06 | V12: 257267.88
A13: ENG-010 | B13: Metro Regional Transit Authority | C13: Fare System Financial Reconciliation Support | D13: Time & Materials | E13: S. Whitfield | F13: 45798 | G13: 46124 | H13: 2748 | I13: 583770 | J13: 587107.14 | K13: 0 | L13: =J13+K13 -> 587107.14 | M13: 0.282 | N13: =SUMIFS('Budget vs Actual'!$F$4:$F$515,'Budget vs Actual'!$A$4:$A$515,A13) -> 2484.9 | O13: =SUMIFS('Budget vs Actual'!$I$4:$I$515,'Budget vs Actual'!$A$4:$A$515,A13) -> 529438 | P13: =IF(H13=0,"",N13/H13) -> 0.90425764 | Q13: =IF(L13=0,"",V13/L13) -> 0.90177408 | R13: =P13-M13 -> 0.62225764 | S13: =IF(P13>1,"Over Budget",IF(R13>0.15,"Trending Over Budget",IF(R13<-0.15,"Behind Pace / Under-Utilized","On Track"))) -> Trending Over Budget | T13: =COUNTIF('Discrepancy Report'!$B$4:$B$67,A13) -> 5 | U13: =SUMIF('Discrepancy Report'!$B$4:$B$67,A13,'Discrepancy Report'!$G$4:$G$67) -> 75100.14 | V13: 529438
A14: ENG-011 | B14: Commonwealth Department of Transportation | C14: Fleet Maintenance Cost Optimization Study | D14: Time & Materials | E14: J. Patel | F14: 45823 | G14: 46274 | H14: 2213 | I14: 472045 | J14: 498726.25 | K14: 0 | L14: =J14+K14 -> 498726.25 | M14: 0.127 | N14: =SUMIFS('Budget vs Actual'!$F$4:$F$515,'Budget vs Actual'!$A$4:$A$515,A14) -> 1304.1 | O14: =SUMIFS('Budget vs Actual'!$I$4:$I$515,'Budget vs Actual'!$A$4:$A$515,A14) -> 274820.5 | P14: =IF(H14=0,"",N14/H14) -> 0.58929056 | Q14: =IF(L14=0,"",V14/L14) -> 0.55104479 | R14: =P14-M14 -> 0.46229056 | S14: =IF(P14>1,"Over Budget",IF(R14>0.15,"Trending Over Budget",IF(R14<-0.15,"Behind Pace / Under-Utilized","On Track"))) -> Trending Over Budget | T14: =COUNTIF('Discrepancy Report'!$B$4:$B$67,A14) -> 3 | U14: =SUMIF('Discrepancy Report'!$B$4:$B$67,A14,'Discrepancy Report'!$G$4:$G$67) -> 12081.5 | V14: 274820.5
A15: ENG-012 | B15: Bureau of Health & Human Services | C15: Benefits Program Financial Audit Support | D15: Time & Materials | E15: R. Chen | F15: 45699 | G15: 45983 | H15: 1390 | I15: 294840 | J15: 322356.22 | K15: 0 | L15: =J15+K15 -> 322356.22 | M15: 0.761 | N15: =SUMIFS('Budget vs Actual'!$F$4:$F$515,'Budget vs Actual'!$A$4:$A$515,A15) -> 1231.3 | O15: =SUMIFS('Budget vs Actual'!$I$4:$I$515,'Budget vs Actual'!$A$4:$A$515,A15) -> 260508.5 | P15: =IF(H15=0,"",N15/H15) -> 0.88582734 | Q15: =IF(L15=0,"",V15/L15) -> 0.80813859 | R15: =P15-M15 -> 0.12482734 | S15: =IF(P15>1,"Over Budget",IF(R15>0.15,"Trending Over Budget",IF(R15<-0.15,"Behind Pace / Under-Utilized","On Track"))) -> On Track | T15: =COUNTIF('Discrepancy Report'!$B$4:$B$67,A15) -> 4 | U15: =SUMIF('Discrepancy Report'!$B$4:$B$67,A15,'Discrepancy Report'!$G$4:$G$67) -> 9780.5 | V15: 260508.5
... A21: ENG-018 | B21: Federal Logistics & Readiness Agency | C21: Financial Systems Audit Readiness | D21: Cost-Plus-Fixed-Fee | E21: J. Patel | F21: 45701 | G21: 45900 | H21: 603 | I21: 128000 | J21: 82503.54 | K21: 0 | L21: =J21+K21 -> 82503.54 | M21: 1 | N21: =SUMIFS('Budget vs Actual'!$F$4:$F$515,'Budget vs Actual'!$A$4:$A$515,A21) -> 491.6 | O21: =SUMIFS('Budget vs Actual'!$I$4:$I$515,'Budget vs Actual'!$A$4:$A$515,A21) -> 103809 | P21: =IF(H21=0,"",N21/H21) -> 0.81525705 | Q21: =IF(L21=0,"",V21/L21) -> 0.75433781 | R21: =P21-M21 -> -0.18474295 | S21: =IF(P21>1,"Over Budget",IF(R21>0.15,"Trending Over Budget",IF(R21<-0.15,"Behind Pace / Under-Utilized","On Track"))) -> Behind Pace / Under-Utilized | T21: =COUNTIF('Discrepancy Report'!$B$4:$B$67,A21) -> 3 | U21: =SUMIF('Discrepancy Report'!$B$4:$B$67,A21,'Discrepancy Report'!$G$4:$G$67) -> 22436.12 | V21: 62235.54

Sheet Budget vs Actual
A1: Budget vs Actual -- by Engagement, Role, Month
A2: Synthetic data, as of 2025-08-15
A3: Engagement ID | B3: Client | C3: Role | D3: Month | E3: Budgeted Hours | F3: Actual Hours | G3: Utilization % | H3: Budgeted $ | I3: Actual $ (Standard Rate) | J3: Actual $ (Recorded Rate) | K3: Rate Realization %
A4: ENG-001 | B4: Commonwealth Department of Transportation | C4: Associate | D4: 45566 | E4: 47.2 | F4: 43 | G4: =IF(E4=0,"",F4/E4) -> 0.91101695 | H4: 7316.05 | I4: 6665 | J4: 6665 | K4: =IF(I4=0,"",J4/I4) -> 1
A5: ENG-001 | B5: Commonwealth Department of Transportation | C5: Consultant | D5: 45566 | E5: 56.89 | F5: 39.3 | G5: =IF(E5=0,"",F5/E5) -> 0.69080682 | H5: 11947.1 | I5: 8253 | J5: 8253 | K5: =IF(I5=0,"",J5/I5) -> 1
A6: ENG-001 | B6: Commonwealth Department of Transportation | C6: Manager | D6: 45566 | E6: 26.7 | F6: 18.6 | G6: =IF(E6=0,"",F6/E6) -> 0.69662921 | H6: 7342.09 | I6: 5115 | J6: 5115 | K6: =IF(I6=0,"",J6/I6) -> 1
A7: ENG-001 | B7: Commonwealth Department of Transportation | C7: Partner | D7: 45566 | E7: 7.91 | F7: 2.9 | G7: =IF(E7=0,"",F7/E7) -> 0.36662453 | H7: 3045.61 | I7: 1116.5 | J7: 1116.5 | K7: =IF(I7=0,"",J7/I7) -> 1
A8: ENG-001 | B8: Commonwealth Department of Transportation | C8: Associate | D8: 45597 | E8: 80.71 | F8: 74.3 | G8: =IF(E8=0,"",F8/E8) -> 0.92057985 | H8: 12510.39 | I8: 11516.5 | J8: 11516.5 | K8: =IF(I8=0,"",J8/I8) -> 1
A9: ENG-001 | B9: Commonwealth Department of Transportation | C9: Consultant | D9: 45597 | E9: 97.28 | F9: 88.1 | G9: =IF(E9=0,"",F9/E9) -> 0.90563322 | H9: 20429.43 | I9: 18501 | J9: 18501 | K9: =IF(I9=0,"",J9/I9) -> 1
A10: ENG-001 | B10: Commonwealth Department of Transportation | C10: Manager | D10: 45597 | E10: 45.65 | F10: 44.7 | G10: =IF(E10=0,"",F10/E10) -> 0.97918949 | H10: 12554.92 | I10: 12292.5 | J10: 12292.5 | K10: =IF(I10=0,"",J10/I10) -> 1
A11: ENG-001 | B11: Commonwealth Department of Transportation | C11: Partner | D11: 45597 | E11: 13.53 | F11: 12.7 | G11: =IF(E11=0,"",F11/E11) -> 0.93865484 | H11: 5207.97 | I11: 4889.5 | J11: 4889.5 | K11: =IF(I11=0,"",J11/I11) -> 1
A12: ENG-001 | B12: Commonwealth Department of Transportation | C12: Associate | D12: 45627 | E12: 107.59 | F12: 73.1 | G12: =IF(E12=0,"",F12/E12) -> 0.67943117 | H12: 16675.93 | I12: 11330.5 | J12: 11330.5 | K12: =IF(I12=0,"",J12/I12) -> 1
A13: ENG-001 | B13: Commonwealth Department of Transportation | C13: Consultant | D13: 45627 | E13: 129.67 | F13: 107.2 | G13: =IF(E13=0,"",F13/E13) -> 0.82671397 | H13: 27231.74 | I13: 22512 | J13: 22512 | K13: =IF(I13=0,"",J13/I13) -> 1
A14: ENG-001 | B14: Commonwealth Department of Transportation | C14: Manager | D14: 45627 | E14: 60.86 | F14: 53.7 | G14: =IF(E14=0,"",F14/E14) -> 0.88235294 | H14: 16735.28 | I14: 14767.5 | J14: 14767.5 | K14: =IF(I14=0,"",J14/I14) -> 1
A15: ENG-001 | B15: Commonwealth Department of Transportation | C15: Partner | D15: 45627 | E15: 18.03 | F15: 17.6 | G15: =IF(E15=0,"",F15/E15) -> 0.97615086 | H15: 6942.04 | I15: 6776 | J15: 6776 | K15: =IF(I15=0,"",J15/I15) -> 1
... A515: ENG-018 | B515: Federal Logistics & Readiness Agency | C515: Partner | D515: 45870 | E515: 2.75 | F515: 2.7 | G515: =IF(E515=0,"",F515/E515) -> 0.98181818 | H515: 1057.45 | I515: 1039.5 | J515: 1039.5 | K515: =IF(I515=0,"",J515/I515) -> 1

Sheet Sample Invoice
A1: Meridian Advisory Partners
A2: 1200 Market Street, Suite 900, Washington, DC 20005
A4: CLIENT INVOICE
A5: DRAFT -- pending engagement leader review
A7: Invoice #: | B7: INV-ENG-010-202507 | D7: Invoice Date: | E7: 45874
A8: Bill To: | B8: Metro Regional Transit Authority | D8: Billing Period: | E8: 2025-07-01 to 2025-07-31
A9: Engagement: | B9: Fare System Financial Reconciliation Support | D9: Engagement ID: | E9: ENG-010
A10: Contract Type: | B10: Time & Materials | D10: Engagement Leader: | E10: S. Whitfield
A13: Description | B13: Category | C13: Role | D13: Hours | E13: Rate | F13: Amount
A14: Professional Services -- Partner | B14: Labor | C14: Partner | D14: 54.5 | E14: 385 | F14: =D14*E14 -> 20982.5
A15: Professional Services -- Manager | B15: Labor | C15: Manager | D15: 141.9 | E15: 275 | F15: =D15*E15 -> 39022.5
A16: Professional Services -- Consultant | B16: Labor | C16: Consultant | D16: 377.1 | E16: 210 | F16: =D16*E16 -> 79191
A17: Professional Services -- Associate | B17: Labor | C17: Associate | D17: 287 | E17: 155 | F17: =D17*E17 -> 44485
A18: Reimbursable Expenses -- Ground Transport | B18: Expense | F18: 89.73
A20: Subtotal -- Labor | F20: =SUMIF(B14:B18,"Labor",F14:F18) -> 183681
A21: Subtotal -- Expenses | F21: =SUMIF(B14:B18,"Expense",F14:F18) -> 89.73
A23: TOTAL AMOUNT DUE | F23: =F20+F21 -> 183770.73
A26: This draft invoice reflects hours and expenses recorded as approved and correctly coded in the firm's timekeeping system as of the billing period close. Every line item traces back to specific timesheet/expense records; see reconcile_invoice_to_source() in invoicing.py.

Sheet Discrepancy Report
A1: Discrepancy & Exception Report
A2: Prioritized by severity, then dollar impact -- as of 2025-08-15. Synthetic data for demonstration only.
A3: Discrepancy ID | B3: Engagement ID | C3: Client | D3: Engagement Leader | E3: Category | F3: Severity | G3: Dollar Impact | H3: Description | I3: Recommended Action | J3: Detected Date | M3: Escalation Summary by Engagement Leader
A4: DQ-UNBILL-ENG-009 | B4: ENG-009 | C4: Ashford County Government | D4: D. Okoro | E4: Unbilled Time Aging | F4: High | G4: 79722 | H4: $79,722.00 of approved, billable time (369.2 hrs) has not been invoiced, oldest entry 106 days old. | I4: Include in next billing cycle; if a prior invoice run missed this work, investigate why. | J4: 45884 | M4: Leader | N4: Open Exceptions | O4: High | P4: Medium | Q4: Low | R4: Total $ Impact | S4: Engagements Affected
A5: DQ-UNBILL-ENG-018 | B5: ENG-018 | C5: Federal Logistics & Readiness Agency | D5: J. Patel | E5: Unbilled Time Aging | F5: High | G5: 20410.5 | H5: $20,410.50 of approved, billable time (95.2 hrs) has not been invoiced, oldest entry 73 days old. | I5: Include in next billing cycle; if a prior invoice run missed this work, investigate why. | J5: 45884 | M5: R. Chen | N5: 28 | O5: 7 | P5: 14 | Q5: 7 | R5: 80911.5 | S5: 7
A6: DQ-APPR-ENG-006 | B6: ENG-006 | C6: Commonwealth Department of Transportation | D6: R. Chen | E6: Missing Approval | F6: High | G6: 6656 | H6: 5 time entries are unapproved, oldest 205 days past the work date (normal cycle is 14 days). | I6: Escalate to approving manager for immediate sign-off; time cannot be billed until approved. | J6: 45884 | M6: J. Patel | N6: 8 | O6: 4 | P6: 2 | Q6: 2 | R6: 38263.62 | S6: 3
A7: DQ-APPR-ENG-012 | B7: ENG-012 | C7: Bureau of Health & Human Services | D7: R. Chen | E7: Missing Approval | F7: High | G7: 5623 | H7: 6 time entries are unapproved, oldest 127 days past the work date (normal cycle is 14 days). | I7: Escalate to approving manager for immediate sign-off; time cannot be billed until approved. | J7: 45884 | M7: D. Okoro | N7: 10 | O7: 3 | P7: 4 | Q7: 3 | R7: 112927.06 | S7: 2
A8: DQ-APPR-ENG-010 | B8: ENG-010 | C8: Metro Regional Transit Authority | D8: S. Whitfield | E8: Missing Approval | F8: High | G8: 5460 | H8: 5 time entries are unapproved, oldest 77 days past the work date (normal cycle is 14 days). | I8: Escalate to approving manager for immediate sign-off; time cannot be billed until approved. | J8: 45884 | M8: M. Alvarez | N8: 10 | O8: 3 | P8: 4 | Q8: 3 | R8: 28838.5 | S8: 3
A9: DQ-APPR-ENG-009 | B9: ENG-009 | C9: Ashford County Government | D9: D. Okoro | E9: Missing Approval | F9: High | G9: 5272 | H9: 5 time entries are unapproved, oldest 247 days past the work date (normal cycle is 14 days). | I9: Escalate to approving manager for immediate sign-off; time cannot be billed until approved. | J9: 45884 | M9: S. Whitfield | N9: 8 | O9: 2 | P9: 4 | Q9: 2 | R9: 78698.14 | S9: 2
A10: DQ-APPR-ENG-015 | B10: ENG-015 | C10: Metro Regional Transit Authority | D10: R. Chen | E10: Missing Approval | F10: High | G10: 5127.5 | H10: 4 time entries are unapproved, oldest 200 days past the work date (normal cycle is 14 days). | I10: Escalate to approving manager for immediate sign-off; time cannot be billed until approved. | J10: 45884
A11: DQ-APPR-ENG-011 | B11: ENG-011 | C11: Commonwealth Department of Transportation | D11: J. Patel | E11: Missing Approval | F11: High | G11: 3861.5 | H11: 4 time entries are unapproved, oldest 74 days past the work date (normal cycle is 14 days). | I11: Escalate to approving manager for immediate sign-off; time cannot be billed until approved. | J11: 45884
A12: DQ-APPR-ENG-003 | B12: ENG-003 | C12: Federal Logistics & Readiness Agency | D12: M. Alvarez | E12: Missing Approval | F12: High | G12: 3148.5 | H12: 4 time entries are unapproved, oldest 51 days past the work date (normal cycle is 14 days). | I12: Escalate to approving manager for immediate sign-off; time cannot be billed until approved. | J12: 45884
A13: DQ-APPR-ENG-016 | B13: ENG-016 | C13: Commonwealth Department of Transportation | D13: D. Okoro | E13: Missing Approval | F13: High | G13: 2734 | H13: 3 time entries are unapproved, oldest 163 days past the work date (normal cycle is 14 days). | I13: Escalate to approving manager for immediate sign-off; time cannot be billed until approved. | J13: 45884
A14: DQ-APPR-ENG-008 | B14: ENG-008 | C14: Federal Logistics & Readiness Agency | D14: R. Chen | E14: Missing Approval | F14: High | G14: 2612.5 | H14: 3 time entries are unapproved, oldest 86 days past the work date (normal cycle is 14 days). | I14: Escalate to approving manager for immediate sign-off; time cannot be billed until approved. | J14: 45884
A15: DQ-APPR-ENG-004 | B15: ENG-004 | C15: Ashford County Government | D15: M. Alvarez | E15: Missing Approval | F15: High | G15: 2436 | H15: 2 time entries are unapproved, oldest 282 days past the work date (normal cycle is 14 days). | I15: Escalate to approving manager for immediate sign-off; time cannot be billed until approved. | J15: 45884
A16: DQ-APPR-ENG-001 | B16: ENG-001 | C16: Commonwealth Department of Transportation | D16: M. Alvarez | E16: Missing Approval | F16: High | G16: 2233 | H16: 1 time entry is unapproved, oldest 190 days past the work date (normal cycle is 14 days). | I16: Escalate to approving manager for immediate sign-off; time cannot be billed until approved. | J16: 45884
A17: DQ-APPR-ENG-002 | B17: ENG-002 | C17: Bureau of Health & Human Services | D17: R. Chen | E17: Missing Approval | F17: High | G17: 1848 | H17: 2 time entries are unapproved, oldest 108 days past the work date (normal cycle is 14 days). | I17: Escalate to approving manager for immediate sign-off; time cannot be billed until approved. | J17: 45884
A18: DQ-APPR-ENG-013 | B18: ENG-013 | C18: Federal Logistics & Readiness Agency | D18: J. Patel | E18: Missing Approval | F18: High | G18: 1821 | H18: 2 time entries are unapproved, oldest 74 days past the work date (normal cycle is 14 days). | I18: Escalate to approving manager for immediate sign-off; time cannot be billed until approved. | J18: 45884
A19: DQ-APPR-ENG-017 | B19: ENG-017 | C19: Bureau of Health & Human Services | D19: S. Whitfield | E19: Missing Approval | F19: High | G19: 1119.5 | H19: 2 time entries are unapproved, oldest 128 days past the work date (normal cycle is 14 days). | I19: Escalate to approving manager for immediate sign-off; time cannot be billed until approved. | J19: 45884
A20: DQ-APPR-ENG-014 | B20: ENG-014 | C20: Ashford County Government | D20: R. Chen | E20: Missing Approval | F20: High | G20: 1045 | H20: 1 time entry is unapproved, oldest 88 days past the work date (normal cycle is 14 days). | I20: Escalate to approving manager for immediate sign-off; time cannot be billed until approved. | J20: 45884
A21: DQ-APPR-ENG-018 | B21: ENG-018 | C21: Federal Logistics & Readiness Agency | D21: J. Patel | E21: Missing Approval | F21: High | G21: 821.5 | H21: 2 time entries are unapproved, oldest 128 days past the work date (normal cycle is 14 days). | I21: Escalate to approving manager for immediate sign-off; time cannot be billed until approved. | J21: 45884
... A67: DQ-UNBILLEXP-ENG-009 | B67: ENG-009 | C67: Ashford County Government | D67: D. Okoro | E67: Unbilled Expense Aging | F67: Low | G67: 409.06 | H67: $409.06 of approved, billable expenses have not been invoiced (oldest 99 days). | I67: Include in next billing cycle. | J67: 45884
